{
    "display": {
        "icon": {
            "item": "dragonfire:mummy_head"
        },
        "title": {
            "translate": "advancements.dragonfire.kill_a_mummy.title"
        },
        "description": {
            "translate": "advancements.dragonfire.kill_a_mummy.description"
        }
    },
    "parent": "dragonfire:root",
    "criteria": {
        "cave_spider": {
            "trigger": "minecraft:player_killed_entity",
            "conditions": {
                "entity": {
                    "type": "dragonfire:mummy"
                }
            }
        },
        "spider": {
            "trigger": "minecraft:player_killed_entity",
            "conditions": {
                "entity": {
                    "type": "dragonfire:mummy"
                }
            }
        },
        "zombie_pigman": {
            "trigger": "minecraft:player_killed_entity",
            "conditions": {
                "entity": {
                    "type": "dragonfire:mummy"
                }
            }
        },
        "enderman": {
            "trigger": "minecraft:player_killed_entity",
            "conditions": {
                "entity": {
                    "type": "dragonfire:mummy"
                }
            }
        },
        "polar_bear": {
            "trigger": "minecraft:player_killed_entity",
            "conditions": {
                "entity": {
                    "type": "dragonfire:mummy"
                }
            }
        },
        "blaze": {
            "trigger": "minecraft:player_killed_entity",
            "conditions": {
                "entity": {
                    "type": "dragonfire:mummy"
                }
            }
        },
        "creeper": {
            "trigger": "minecraft:player_killed_entity",
            "conditions": {
                "entity": {
                    "type": "dragonfire:mummy"
                }
            }
        },
        "evoker": {
            "trigger": "minecraft:player_killed_entity",
            "conditions": {
                "entity": {
                    "type": "dragonfire:mummy"
                }
            }
        },
        "ghast": {
            "trigger": "minecraft:player_killed_entity",
            "conditions": {
                "entity": {
                    "type": "dragonfire:mummy"
                }
            }
        },
        "guardian": {
            "trigger": "minecraft:player_killed_entity",
            "conditions": {
                "entity": {
                    "type": "dragonfire:mummy"
                }
            }
        },
        "husk": {
            "trigger": "minecraft:player_killed_entity",
            "conditions": {
                "entity": {
                    "type": "dragonfire:mummy"
                }
            }
        },
        "magma_cube": {
            "trigger": "minecraft:player_killed_entity",
            "conditions": {
                "entity": {
                    "type": "dragonfire:mummy"
                }
            }
        },
        "shulker": {
            "trigger": "minecraft:player_killed_entity",
            "conditions": {
                "entity": {
                    "type": "dragonfire:mummy"
                }
            }
        },
        "silverfish": {
            "trigger": "minecraft:player_killed_entity",
            "conditions": {
                "entity": {
                    "type": "dragonfire:mummy"
                }
            }
        },
        "skeleton": {
            "trigger": "minecraft:player_killed_entity",
            "conditions": {
                "entity": {
                    "type": "dragonfire:mummy"
                }
            }
        },
        "slime": {
            "trigger": "minecraft:player_killed_entity",
            "conditions": {
                "entity": {
                    "type": "dragonfire:mummy"
                }
            }
        },
        "stray": {
            "trigger": "minecraft:player_killed_entity",
            "conditions": {
                "entity": {
                    "type": "dragonfire:mummy"
                }
            }
        },
        "vindicator": {
            "trigger": "minecraft:player_killed_entity",
            "conditions": {
                "entity": {
                    "type": "dragonfire:mummy"
                }
            }
        },
        "witch": {
            "trigger": "minecraft:player_killed_entity",
            "conditions": {
                "entity": {
                    "type": "dragonfire:mummy"
                }
            }
        },
        "wither_skeleton": {
            "trigger": "minecraft:player_killed_entity",
            "conditions": {
                "entity": {
                    "type": "dragonfire:mummy"
                }
            }
        },
        "zombie": {
            "trigger": "minecraft:player_killed_entity",
            "conditions": {
                "entity": {
                    "type": "dragonfire:mummy"
                }
            }
        },
        "zombie_villager": {
            "trigger": "minecraft:player_killed_entity",
            "conditions": {
                "entity": {
                    "type": "dragonfire:mummy"
                }
            }
        }
    },
    "requirements": [
        [
            "cave_spider",
            "spider",
            "zombie_pigman",
            "enderman",
            "polar_bear",
            "blaze",
            "creeper",
            "evoker",
            "ghast",
            "guardian",
            "husk",
            "magma_cube",
            "shulker",
            "silverfish",
            "skeleton",
            "slime",
            "stray",
            "vindicator",
            "witch",
            "wither_skeleton",
            "zombie",
            "zombie_villager"
        ]
    ]
}